RPAwithComputerVision/__init__.py
RPAwithComputerVision/excute.py
RPAwithComputerVision/utils.py
RPAwithComputerVision/vision_ui.py
RPAwithComputerVision/Anchor_matching/Anchor_matching.py
RPAwithComputerVision/Anchor_matching/__init__.py
RPAwithComputerVision/Authenticate/Decryption.py
RPAwithComputerVision/Authenticate/Encryption.py
RPAwithComputerVision/Authenticate/__init__.py
RPAwithComputerVision/Authenticate/authenticate.py
RPAwithComputerVision/Authenticate/send_email.py
RPAwithComputerVision/Blueprinting/Add_n_correct_ui.py
RPAwithComputerVision/Blueprinting/Blueprint.py
RPAwithComputerVision/Blueprinting/Get_ui_info.py
RPAwithComputerVision/Blueprinting/__init__.py
RPAwithComputerVision/Classes/Clean_boxes.py
RPAwithComputerVision/Classes/Common.py
RPAwithComputerVision/Classes/Fill_dictonary.py
RPAwithComputerVision/Classes/Models.py
RPAwithComputerVision/Classes/Ocr_operations.py
RPAwithComputerVision/Classes/Predict_classes.py
RPAwithComputerVision/Classes/Preprocessing.py
RPAwithComputerVision/Classes/Tag_Labels.py
RPAwithComputerVision/Classes/UI_Detection_Result.py
RPAwithComputerVision/Classes/__init__.py
RPAwithComputerVision/Common/Get_appnames.py
RPAwithComputerVision/Common/Open_application.py
RPAwithComputerVision/Common/Open_browser.py
RPAwithComputerVision/Common/Open_vm_app.py
RPAwithComputerVision/Common/Tkinter_windows.py
RPAwithComputerVision/Common/__init__.py
RPAwithComputerVision/Generate_blueprint/Create_blueprint.py
RPAwithComputerVision/Generate_blueprint/__init__.py
RPAwithComputerVision/Models/__init__.py
RPAwithComputerVision/Rpa_automation/Compare_text_ui.py
RPAwithComputerVision/Rpa_automation/Data_extraction.py
RPAwithComputerVision/Rpa_automation/Rpa_actions.py
RPAwithComputerVision/Rpa_automation/Screen_info.py
RPAwithComputerVision/Rpa_automation/Screen_mapping_functions.py
RPAwithComputerVision/Rpa_automation/Sreen_map_test.py
RPAwithComputerVision/Rpa_automation/__init__.py
RPAwithComputerVision-0.0.4.dist-info/METADATA
RPAwithComputerVision-0.0.4.dist-info/WHEEL
RPAwithComputerVision-0.0.4.dist-info/top_level.txt
RPAwithComputerVision-0.0.4.dist-info/RECORD
