Metadata-Version: 2.1
Name: RPAwithComputerVision
Version: 0.0.4
Summary: This is code with package
Home-page: UNKNOWN
Author: botways
License: UNKNOWN
Platform: UNKNOWN
Requires-Dist: easyocr
Requires-Dist: tensorflow
Requires-Dist: sklearn
Requires-Dist: pandas
Requires-Dist: fuzzywuzzy
Requires-Dist: pytesseract
Requires-Dist: pycryptodome
Requires-Dist: selenium
Requires-Dist: keyboard
Requires-Dist: pyautogui
Requires-Dist: pywinauto
Requires-Dist: pywin32 (==300)
Requires-Dist: opencv-python
Requires-Dist: imutils
Requires-Dist: webdriver-manager
